ctxl/__init__.py
ctxl/ctxl.py
ctxl/dependency_analyzer.py
ctxl/preset_manager.py
ctxl-0.3.0.dist-info/METADATA
ctxl-0.3.0.dist-info/WHEEL
ctxl-0.3.0.dist-info/entry_points.txt
ctxl-0.3.0.dist-info/top_level.txt
ctxl-0.3.0.dist-info/RECORD
