Metadata-Version: 2.1
Name: ctxl
Version: 0.3.0
Summary: A CLI tool to dump projects into an LLM ideal format.
Author-email: Binal Patel <binalkp91@gmail.com>
License: Apache-2.0
Project-URL: Homepage, https://github.com/caesarnine/ctxl
Project-URL: Bug Tracker, https://github.com/caesarnine/ctxl/issues
Project-URL: Repository, https://github.com/caesarnine/ctxl.git
Project-URL: Documentation, https://github.com/caesarnine/ctxl#readme
Keywords: cli,folder,structure
Classifier: Programming Language :: Python :: 3
Classifier: License :: OSI Approved :: MIT License
Classifier: Operating System :: OS Independent
Requires-Python: >=3.6
Requires-Dist: pathspec
Requires-Dist: PyYAML
